solcoin/__init__.py
solcoin/buy_tokens.py
solcoin/close_accounts.py
solcoin/create_tokens.py
solcoin/listen_pf_mints.py
solcoin/listen_pf_trades.py
solcoin/sell_tokens.py
solcoin/transfer_sol.py
solcoin-0.2.3.dist-info/METADATA
solcoin-0.2.3.dist-info/WHEEL
solcoin-0.2.3.dist-info/top_level.txt
solcoin-0.2.3.dist-info/RECORD
