Metadata-Version: 2.4
Name: solcoin
Version: 0.2.3
Summary: A package for Solana transactions token transactions
Home-page: https://github.com/bear102/solcoin
Author: bear102
License: MIT
Requires-Dist: solders
Requires-Dist: solana==0.35.1
Requires-Dist: borsh_construct
Requires-Dist: requests
Requires-Dist: construct
Requires-Dist: segment-analytics-python
Dynamic: author
Dynamic: description
Dynamic: description-content-type
Dynamic: home-page
Dynamic: license
Dynamic: requires-dist
Dynamic: summary
